kolore/__init__.py
kolore/__main__.py
kolore/cli.py
kolore/krita.py
kolore/main.py
kolore/palette.py
kolore/png.py
kolore/resources/krita/mimetype
kolore/resources/krita/profiles.xml
kolore/resources/krita/sRGB-elle-V2-srgbtrc.icc
kolore/unity.py
kolore-0.1.14.dist-info/entry_points.txt
kolore-0.1.14.dist-info/WHEEL
kolore-0.1.14.dist-info/METADATA
kolore-0.1.14.dist-info/RECORD
