Metadata-Version: 2.1
Name: kolore
Version: 0.1.14
Summary: Your tiny swiss-army knife for color palettes.
Home-page: https://gitlab.com/AlvarBer/kolore
License: MIT
Keywords: colors,palette,krita,image,unity
Author: AlvarBer
Author-email: git@alvarber.com
Requires-Python: >=3.9,<4.0
Classifier: License :: OSI Approved :: MIT License
Classifier: Programming Language :: Python :: 3
Classifier: Programming Language :: Python :: 3.9
Requires-Dist: Pillow (>=8.1.0,<9.0.0)
Requires-Dist: PyYAML (>=5.4.1,<6.0.0)
Requires-Dist: click (>=7.1.2,<8.0.0)
Project-URL: Repository, https://gitlab.com/AlvarBer/kolore
